{"title":"辽宁省反右派斗争向深入发展","date":"1957-8-2","authors":[],"contents":[{"text":"辽宁省反右派斗争向深入发展","type":"title"},{"text":"新华社沈陽2日訊　辽宁省的反右派斗爭正向深入發展。","type":"paragraph"},{"text":"辽宁省發現的右派分子愈来愈多。7月初旬統計时，仅八十五人，7月中旬卽达五百多人，7月下旬又升到六百多人，到現在为止，全省已發現了三十七个反党小集团、一千零三十五名右派分子，其中極右派一百五十五人。（其中党員占五十一名）。目前各地正繼續深入追挖中。","type":"paragraph"},{"text":"經过群众的說理斗爭，有的右派分子已經繳械投降，低头認罪；有的已經孤立；还有的仍在頑抗。","type":"paragraph"},{"text":"从运动發展情况上看，还存在以下三个問題：","type":"paragraph"},{"text":"（1）斗爭發展不平衡。大專学校、民主党派、工商界开展的还好，党群政法机关和工矿差一些，党务部門最差。","type":"paragraph"},{"text":"有些單位强調右派分子沒有暴露，卽不深追，也不發动群众。如錦州市第一貿易公司，为了發現右派分子，在一个晩上卽召开大会，討論了肃反、合作化和統購統銷等五个問題，会上沒人提出反对意見，領导人卽認为沒有右派分子。","type":"paragraph"},{"text":"沈陽市有些單位發現了一兩名右派分子后，卽認为成績不錯，而想草率收兵。","type":"paragraph"},{"text":"（2）有些單位沒有根据不断深入的特点，随时改变斗爭策略。","type":"paragraph"},{"text":"領导一般化，沒能对症下藥，敎育积極分子充分說理不够。在会上只是喊口号，据理駁斥不够，指不出右派分子的錯在那里。有的單位只注意打击明显的，对隐蔽的注意不够。","type":"paragraph"},{"text":"在斗爭中忽略了爭取起义的工作。","type":"paragraph"},{"text":"（3）分类排队工作粗糙，排錯排漏的不在少数，錯的原因是控制不严，界限不淸。有的單位乱打乱点名，有的却以报复态度，划定右派分子。东北地質局、冶金工業部地質局东北分局等單位，召开大会叫群众推荐右派分子。本溪煤矿所屬的一个單位，指定一名非党科長选右派分子，他选了十四名，問他根据时，他答：是根据發展看問題的。","type":"paragraph"},{"text":"漏的原因，是沒有很好掌握标准。但最主要原因是溫情主义，特別是对党內右派分子，下的决心不大。","type":"paragraph"},{"text":"省委領导小組已指示各市，在深入斗爭中一定要深、狠、細致、改进工作。","type":"paragraph"},{"text":"1.斗争尙未展开的單位，要糾正右傾情緒鼓起勁头。","type":"paragraph"},{"text":"2.斗争已深入或处于“頂牛狀态的單位，要防止喊口号、駡人的現象，坚决制止动手打人現象。防止乱点名。对确已低头認罪的，适可而止，給予認罪改造机会。","type":"paragraph"},{"text":"3.适当地再开辟一些战場，着重在中等厂矿和財貿企業部門。厂矿主要是搞技职人員。4.斗爭方法主要是發动群众，深追深挖，挖集团，挖自由市場（黑市）。多用小会形式，开大会要經市委批准。","type":"paragraph"},{"text":"5.加强排队工作的領导，严格控制。","type":"paragraph"},{"text":"需經市委批准确認为右派分子的，是副处長以上、全市性代表人物、全市性批判的和各單位不敢認定的。","type":"paragraph"},{"text":"（任步芳）","type":"paragraph"},{"text":"來源： 新华通訊社編：《内部参考》，第2276期，1957年8月6日。","type":"paragraph"}]}