{"title":"王亚南在“鳴”、“放”中表現右傾","date":"1957-6-11","authors":[],"contents":[{"text":"王亚南在“鳴”、“放”中表現右傾","type":"title"},{"text":"新华社福州11日电  11日上午中共福建省委在地市委書記紧急会議上研究厦門大学“鳴”、“放”問題时，談到了厦大校長王重南对“鳴”、“放”的表現。王巫南剛在今年5月份被吸收入党。他在这次厦大的“鳴”、“放”分析問題中表現了接近右傾、同情右派。厦門市委第一書記張維茲、福建省委書記伍洪群亲自和他談过話，打通思想，要他放手“鳴”、“放”。他对此表示犹豫和不通。后来省委第一書記叶飞曾由渭赶到厦門，和王談話，鼓励他大胆發动“鳴”、“放”。这时王同意“鳴”、“放”，而实际却不行动。王的这种思想，对厦大的“鳴”、“放”有着很不利的影响。","type":"paragraph"},{"text":"省委分析王亞南迟迟不动的原因說：起初王認为厦大没有牛鬼蛇神，后来經过省、市委書記的帮助分析，也認为厦大有牛鬼蛇神，但为右派表面現象所迷惑，不同意用搞乱了的方法把右派甩出来。他認为要使右派不鬧事，主要的問題是我們作風的轉变，意即不承認这里还有阶級斗爭。于是他对“鳴”、“放”不积極，不热忱。王是全国人民代表大会代表，几次提出提前于6日程到京开人民代表大会，其中目的之一是想到上海等地寻聘几个好的敎授，拟把厦大的右派分子換出法。省委几个負責同志認为王忠于祖国是个好人，只是犯了敎条主义，致看不清敌人。同时認为王的認識是可以轉变的，但其本人若得不到敎訓，則轉变是不容易的。現省委和厦大党委确定專人对王进行說服。(徐曉)","type":"paragraph"},{"text":"來源：新华通訊社編：《内部参考》，第2229期，1957年6月13日。","type":"paragraph"}]}