{"title":"福建农村点滴","date":"1957-10-3","authors":[],"contents":[{"text":"福建农村点滴","type":"title"},{"text":"新华社福州３日訊  福建农村点滴。","type":"paragraph"},{"text":"（一）划分新上中农的标准不一","type":"subtitle"},{"text":"据中共福州市委宣傳部郑潤生反映：福州市郊鼓山、象园等乡农業社在开展社会主义大辯論、分析当前农村阶級情况时，發生划分新中农的标准不一致的問題。鼓山乡几个农業社在討論中有兩种意見：一种認为应以合作化后生活上升情况是否超过一般农民生活水平作为划分标准；一种意見則認为富裕中农的特点是：除了生活富裕外，还有輕微剝削行为，有較严重的資本主义思想傾向，因此划分新上中农应着重生活較富裕的社員有無投机活动以及对合作化态度如何来决定。鼓山第五农業社按前一种意見划分，結果全社有近一半的社員都是新上中农；远洋农業社按后一种意見划分，結果新上中农只占社員总数５％。象园乡大坂农業社划分新上中农的标准則与鼓山、远洋社基本相同：一看生活水平；二看有無剝削行为；三看对合作化的态度。三者相互联系，并根据当地情况，訂出生活水平的标准是：凡全家每月每人平均收入在十元左右的为下中农，十五元以上的为富裕中农。根据这个标准划分結果，全社一百一十八戶社員中有二十四戶是新上中农，加上七戶老上中农，全社新老上中农共占２６％強。","type":"paragraph"},{"text":"又据福建日报編輯部了解，其他县（市）有的乡也存在类似問題，上中农所占的比例很大。","type":"paragraph"},{"text":"（三）“五保戶”死后遺产归社","type":"subtitle"},{"text":"据中共龙岩县委会黄岩来信反映：龙岩县匯石乡河南农業社在預分方案中會規定：“凡五保戶的社員死了后，財产、园地要归农業社集体所有＂，另外有些社虽無明文規定，但也流傳着这种說法。因此有的社对不該享受“五保＂的也給予“五保＂待遇了，有些社員在听説“五保戶＂死后財产要归社就不願享受“五保＂，或不讓亲屬当“五保戶＂。河南农業社有个老太婆，三个兒子都不撫养她，原来靠救济和农業社帮助过活，这次农業社要評她为“五保戶＂，她三个兒子知道后就說：“农業社説什么五保，只不过貪圖人家死后有財产可得而已＂，并申明：“我母亲不要五保，由我們兄弟輪流供养好了＂。与河南社鄰近的苏邦农業社“五保戶＂，七十多岁的老寡妇陈向地听到这个消息后也怕死后財产归社所有，就搬到别处去住，并把自己的住房拆卖掉。 （陈啓桐）","type":"paragraph"},{"text":"新华通讯社编：《内部参考》，第2328期，1957年10月9日。","type":"paragraph"}]}