{"title":"反对土地改革运动的右派言论","date":"1957-6-0","authors":["河南医学院","周炳生","黄咏平","张云","张治江"],"contents":[{"text":"反对土地改革运动的右派言论","type":"title"},{"text":["河南医学院","周炳生","黄咏平","张云","张治江"],"type":"authors"},{"text":"土改偏激了。(周炳生，26期学生)","type":"paragraph"},{"text":"河南土改搞糟了。(黄咏平，25期学生)","type":"paragraph"},{"text":"河南土改搞得乱七八糟。(张云，25期学生)","type":"paragraph"},{"text":"土改时要是你是地主，乡政府，要枪毙你就枪毙，那时杀人没数，地主人家有钱，他的地也不是抢来的，把人家的东西弄走还不讲，还说地主剥削人，农民是自私，见钱不要命。(张治江，26期学生)","type":"paragraph"},{"text":"土改时他(指党)把人们划成几个人群，叫你相互斗争，叫农民斗地主，给你点东西，替我干吧！(张治江)","type":"paragraph"},{"text":"来源：《右派言论集》（河南医学院马列主义教研室编印，1958年4月）。","type":"appellation"}]}