{"title":"毛泽东对湖北省委关于做好当前人民生活的几项工作的规定的批语","date":"1958-11-21","authors":[],"contents":[{"text":"毛泽东对湖北省委关于做好当前人民生活的几项工作的规定的批语","type":"title"},{"text":"一","type":"subtitle"},{"text":"此件很好。请小平同志阅后，印发到会各同志，加以研究。","type":"paragraph"},{"text":" 毛泽东1958年11月21日","type":"paragraph"},{"text":"二","type":"subtitle"},{"text":"退小平同志印发。","type":"paragraph"},{"text":" 毛廿七日下午七时","type":"paragraph"},{"text":"既在会〔后〕公布，时间应是十二月某日。","type":"paragraph"},{"text":"来源：","type":"source"},{"text":"根据文件的翻印件打印","type":"paragraph"}]}