{"title":"毛泽东关于了解河北省博野县农业合作社整顿情况的两个批语","date":"1955-9-13","authors":["毛泽东"],"contents":[{"text":"毛泽东关于了解河北省博野县农业合作社整顿情况的两个批语","type":"title"},{"text":["毛泽东"],"type":"authors"},{"text":"一","type":"subtitle"},{"text":"此件送河北省委林铁同志阅。","type":"paragraph"},{"text":"钟顺通是我们这里的一个警卫工作人员。据他说，博野县有些合作社并没有认真去整顿。请省委注意此事，如果属实，应设法加以解决。","type":"paragraph"},{"text":" 毛泽东九月十三日","type":"paragraph"},{"text":"二","type":"subtitle"},{"text":"叶子龙电话告林铁同志：","type":"appellation"},{"text":"此信收到了，谢谢他。","type":"paragraph"},{"text":" 毛泽东十月廿三日","type":"paragraph"}]}