{"title":"对国家经委党组关于工业、交通生产情况报告的批语","date":"1960-2-26","authors":["毛泽东"],"contents":[{"text":"对国家经委党组关于工业、交通生产情况报告的批语","type":"title"},{"text":["毛泽东"],"type":"authors"},{"text":"一","type":"subtitle"},{"text":"周总理：","type":"appellation"},{"text":"这个总结很好，这是一个新方法，应该继续做。一年总结六次，每两个月总结一次，经中央批准通报出去，一定大有推动作用。请你阅后，给你们读书会各同志一阅，然后送薄一波同志一阅。给少奇、小平、彭真一阅。","type":"paragraph"},{"text":" 毛泽东二月廿六日","type":"paragraph"},{"text":"二","type":"subtitle"},{"text":"要大办小洋发电。","type":"paragraph"},{"text":"三","type":"subtitle"},{"text":"争取二千二百万吨钢。","type":"paragraph"},{"text":"来源：","type":"source"},{"text":"根据文件的翻印件打印","type":"paragraph"}]}